quantpunc/__init__.py
quantpunc/combobox_manager.py
quantpunc/napari.yaml
quantpunc/preprocessing.py
quantpunc/quantpunc_widget.py
quantpunc/watershed.py
quantpunc/quantification/abstract_puncta_labeler.py
quantpunc/quantification/colocalization.py
quantpunc/quantification/default_puncta_labelers.py
quantpunc/quantification/puncta_analyzer.py
quantpunc/quantification/puncta_labeler_registry.py
quantpunc/table/table_model_view.py
quantpunc/table/table_widget.py
quantpunc-0.0.1.post1.dist-info/licenses/LICENSE
quantpunc-0.0.1.post1.dist-info/METADATA
quantpunc-0.0.1.post1.dist-info/WHEEL
quantpunc-0.0.1.post1.dist-info/entry_points.txt
quantpunc-0.0.1.post1.dist-info/top_level.txt
quantpunc-0.0.1.post1.dist-info/RECORD
