Metadata-Version: 2.4
Name: quantpunc
Version: 0.0.1.post1
Summary: A Napari plugin for puncta analysis and quantification in 2D microscopy images.
Author: tehahn
License-Expression: BSD-3-Clause
Project-URL: Documentation, https://tehahn.github.io/quantpunc/
Project-URL: Repository, https://github.com/tehahn/quantpunc/
Classifier: Development Status :: 4 - Beta
Classifier: Framework :: napari
Classifier: Intended Audience :: Science/Research
Classifier: Operating System :: OS Independent
Classifier: Programming Language :: Python
Classifier: Programming Language :: Python :: 3
Classifier: Programming Language :: Python :: 3 :: Only
Classifier: Programming Language :: Python :: 3.10
Classifier: Programming Language :: Python :: 3.11
Classifier: Topic :: Scientific/Engineering :: Image Processing
Requires-Python: >=3.10
License-File: LICENSE
Requires-Dist: numpy<2.3
Requires-Dist: magicgui
Requires-Dist: qtpy
Requires-Dist: scikit-image
Requires-Dist: scikit-learn>=1.6.1
Requires-Dist: pywavelets>=1.6.0
Provides-Extra: testing
Requires-Dist: tox; extra == "testing"
Requires-Dist: pytest; extra == "testing"
Requires-Dist: pytest-cov; extra == "testing"
Requires-Dist: pytest-qt; extra == "testing"
Requires-Dist: napari; extra == "testing"
Requires-Dist: pyqt5; extra == "testing"
Dynamic: license-file
